mapper.cpython-38-x86_64-linux-gnu.so
kmer_mapper-0.0.27.dist-info/METADATA
kmer_mapper-0.0.27.dist-info/RECORD
kmer_mapper-0.0.27.dist-info/top_level.txt
kmer_mapper-0.0.27.dist-info/WHEEL
kmer_mapper-0.0.27.dist-info/entry_points.txt
kmer_mapper/numpy_mapping.py
kmer_mapper/hash_table.py
kmer_mapper/mapper.cpython-38-x86_64-linux-gnu.so
kmer_mapper/encodings.py
kmer_mapper/parser.py
kmer_mapper/sequences.py
kmer_mapper/kmer_counting.py
kmer_mapper/mapping.py
kmer_mapper/kmer_lookup.py
kmer_mapper/kmers.py
kmer_mapper/__init__.py
kmer_mapper/gpu_counter.py
kmer_mapper/command_line_interface.py
kmer_mapper/util.py
